gbsd/__init__.py
gbsd/_cuda_utils.py
gbsd/_data.py
gbsd/calculator.py
gbsd/losses.py
gbsd/potentials.py
gbsd/spectra.py
gbsd/structure.py
gbsd-0.2.15.dist-info/LICENSE
gbsd-0.2.15.dist-info/METADATA
gbsd-0.2.15.dist-info/WHEEL
gbsd-0.2.15.dist-info/RECORD
